impossibly/__init__.py
impossibly/agent.py
impossibly/graph.py
impossibly/cli/__init__.py
impossibly/cli/test_commands.py
impossibly/utils/__init__.py
impossibly/utils/memory.py
impossibly/utils/start_end.py
impossibly/utils/tools.py
impossibly-0.1.2.dist-info/licenses/LICENSE
impossibly-0.1.2.dist-info/METADATA
impossibly-0.1.2.dist-info/WHEEL
impossibly-0.1.2.dist-info/entry_points.txt
impossibly-0.1.2.dist-info/top_level.txt
impossibly-0.1.2.dist-info/RECORD
